setup.cfg
setup.py
rum_repoze_what.egg-info/PKG-INFO
rum_repoze_what.egg-info/SOURCES.txt
rum_repoze_what.egg-info/dependency_links.txt
rum_repoze_what.egg-info/entry_points.txt
rum_repoze_what.egg-info/not-zip-safe
rum_repoze_what.egg-info/requires.txt
rum_repoze_what.egg-info/top_level.txt
rumrepozewhat/__init__.py