Metadata-Version: 1.0
Name: rum-repoze-what
Version: 0.0dev
Summary: repoze.what adapters for rum policy
Home-page: UNKNOWN
Author: Alberto Valverde, Michael Brickenstein
Author-email: brickenstein@mfo.de
License: MIT
Platform: UNKNOWN
